buycoins/__init__.py
buycoins/client.py
buycoins/ngnt.py
buycoins/p2p.py
buycoins/wallet.py
buycoins/webhook.py
buycoins/exceptions/__init__.py
buycoins/exceptions/exceptions.py
buycoins/exceptions/utils.py
tests/__init__.py
tests/class_fixtures.py
tests/mock_responses.py
tests/test_ngnt.py
tests/test_p2p.py
tests/test_wallet.py
buycoins_python-0.5.2.dist-info/LICENSE
buycoins_python-0.5.2.dist-info/METADATA
buycoins_python-0.5.2.dist-info/WHEEL
buycoins_python-0.5.2.dist-info/top_level.txt
buycoins_python-0.5.2.dist-info/RECORD
