Metadata-Version: 2.1
Name: buycoins-python
Version: 0.5.2
Summary: Python SDK for the BuyCoin"s API
Home-page: https://github.com/Youngestdev/buycoins-python
Author: Abdulazeez Abdulazeez Adeshina
Author-email: youngestdev@gmail.com
License: MIT
Platform: UNKNOWN
Classifier: License :: OSI Approved :: MIT License
Classifier: Programming Language :: Python :: 3
Classifier: Programming Language :: Python :: 3.6
Classifier: Programming Language :: Python :: 3.7
Requires-Python: >=3.6
Requires-Dist: python-decouple
Requires-Dist: python-graphql-client
Requires-Dist: requests
